edlib.cpython-39-darwin.so
edlib-1.3.9.post1.dist-info/RECORD
edlib-1.3.9.post1.dist-info/WHEEL
edlib-1.3.9.post1.dist-info/top_level.txt
edlib-1.3.9.post1.dist-info/METADATA
