Metadata-Version: 2.1
Name: edlib
Version: 1.3.9.post1
Summary: Lightweight, super fast library for sequence alignment using edit (Levenshtein) distance.
Home-page: https://github.com/Martinsos/edlib
Author: Martin Sosic
Author-email: sosic.martin@gmail.com
License: MIT
Keywords: edit distance levenshtein align sequence bioinformatics
